odoo8_addon_account_invoice_import-8.0.1.0.1-py3.8-nspkg.pth
odoo_addons/account_invoice_import/README.rst
odoo_addons/account_invoice_import/__init__.py
odoo_addons/account_invoice_import/__openerp__.py
odoo_addons/account_invoice_import/account_invoice.py
odoo_addons/account_invoice_import/account_invoice_import_config.py
odoo_addons/account_invoice_import/account_invoice_import_config_view.xml
odoo_addons/account_invoice_import/partner.py
odoo_addons/account_invoice_import/partner_view.xml
odoo_addons/account_invoice_import/i18n/account_invoice_import.pot
odoo_addons/account_invoice_import/i18n/fr.po
odoo_addons/account_invoice_import/i18n/fr.po.old
odoo_addons/account_invoice_import/i18n/pt_BR.po
odoo_addons/account_invoice_import/i18n/sl.po
odoo_addons/account_invoice_import/images/sshot-wizard1.png
odoo_addons/account_invoice_import/scripts/mass_invoice_import.py
odoo_addons/account_invoice_import/security/ir.model.access.csv
odoo_addons/account_invoice_import/security/rule.xml
odoo_addons/account_invoice_import/static/description/icon.png
odoo_addons/account_invoice_import/views/account_invoice.xml
odoo_addons/account_invoice_import/wizard/__init__.py
odoo_addons/account_invoice_import/wizard/account_invoice_import.py
odoo_addons/account_invoice_import/wizard/account_invoice_import_view.xml
odoo8_addon_account_invoice_import-8.0.1.0.1.dist-info/METADATA
odoo8_addon_account_invoice_import-8.0.1.0.1.dist-info/WHEEL
odoo8_addon_account_invoice_import-8.0.1.0.1.dist-info/namespace_packages.txt
odoo8_addon_account_invoice_import-8.0.1.0.1.dist-info/top_level.txt
odoo8_addon_account_invoice_import-8.0.1.0.1.dist-info/RECORD
