Metadata-Version: 2.1
Name: odoo8-addon-account-invoice-import
Version: 8.0.1.0.1
Summary: Import supplier invoices/refunds as PDF or XML files
Home-page: http://www.akretion.com
Author: Akretion,Odoo Community Association (OCA)
Author-email: support@odoo-community.org
License: AGPL-3
Platform: UNKNOWN
Classifier: Programming Language :: Python
Classifier: Framework :: Odoo
Classifier: Framework :: Odoo :: 8.0
Classifier: License :: OSI Approved :: GNU Affero General Public License v3
Requires-Python: ~=2.7
Requires-Dist: odoo8-addon-base-business-document-import
Requires-Dist: odoo (<9.0a,>=8.0a)
